qkan/__init__.py
qkan/feynman.py
qkan/info.py
qkan/kan.py
qkan/py.typed
qkan/qkan.py
qkan/solver.py
qkan/torch_qc.py
qkan/utils.py
qkan-0.1.4.dist-info/licenses/LICENSE
qkan-0.1.4.dist-info/METADATA
qkan-0.1.4.dist-info/WHEEL
qkan-0.1.4.dist-info/top_level.txt
qkan-0.1.4.dist-info/RECORD
