Metadata-Version: 2.4
Name: qkan
Version: 0.1.4
Summary: Quantum-inspired Kolmogorov Arnold Networks
Author-email: Jiun-Cheng Jiang <jcjiang@phys.ntu.edu.tw>
License:                                  Apache License
Project-URL: Homepage, https://github.com/Jim137/qkan
Classifier: Development Status :: 4 - Beta
Classifier: Programming Language :: Python :: 3.10
Classifier: Programming Language :: Python :: 3.11
Classifier: Programming Language :: Python :: 3.12
Classifier: Intended Audience :: Developers
Classifier: Operating System :: OS Independent
Requires-Python: >=3.10
License-File: LICENSE
Requires-Dist: torch>=2.0
Requires-Dist: tqdm
Requires-Dist: matplotlib
Provides-Extra: qml
Requires-Dist: pennylane>=0.37; extra == "qml"
Provides-Extra: dev
Requires-Dist: mypy; extra == "dev"
Requires-Dist: ruff; extra == "dev"
Requires-Dist: isort; extra == "dev"
Requires-Dist: build; extra == "dev"
Requires-Dist: setuptools; extra == "dev"
Requires-Dist: wheel; extra == "dev"
Requires-Dist: twine; extra == "dev"
Provides-Extra: doc
Requires-Dist: sphinx>=8.0; extra == "doc"
Requires-Dist: sphinx-rtd-theme; extra == "doc"
Requires-Dist: sphinx-autodoc-typehints; extra == "doc"
Requires-Dist: nbsphinx; extra == "doc"
Requires-Dist: jupyter; extra == "doc"
Requires-Dist: qiskit[visualization]>=2.0; extra == "doc"
Requires-Dist: transformers; extra == "doc"
Requires-Dist: torchvision; extra == "doc"
Provides-Extra: all
Requires-Dist: qkan[dev,doc,qml]; extra == "all"
Dynamic: license-file
